MANIFEST.in
README.md
setup.py
git_pull/__init__.py
git_pull/exceptions.py
git_pull/git_pull.py
git_pull/utilities.py
git_pull.egg-info/PKG-INFO
git_pull.egg-info/SOURCES.txt
git_pull.egg-info/dependency_links.txt
git_pull.egg-info/top_level.txt
git_pull/__pycache__/__init__.cpython-39.pyc
git_pull/__pycache__/exceptions.cpython-39.pyc
git_pull/__pycache__/git_pull.cpython-39.pyc
git_pull/__pycache__/utilities.cpython-39.pyc
git_pull/resources/chromedriver
git_pull/resources/documentation.yml
git_pull/resources/languages.yml
git_pull/resources/useragents.yml
git_pull/resources/vendor.yml