Metadata-Version: 2.1
Name: git-pull
Version: 1.0.4
Summary: Parallelized web scraper for Github
Home-page: https://github.com/shobrook/git-pull
Author: shobrook
Author-email: shobrookj@gmail.com
License: MIT
Keywords: scraper,web-scraper,github,github-scraper,github-api,parallel
Platform: UNKNOWN
Requires-Python: >=3
